kraken_class/kraken_class.py
kraken_class/test_records.py
kraken_class-0.0.3.dist-info/LICENSE.txt
kraken_class-0.0.3.dist-info/METADATA
kraken_class-0.0.3.dist-info/WHEEL
kraken_class-0.0.3.dist-info/top_level.txt
kraken_class-0.0.3.dist-info/RECORD
