Metadata-Version: 2.1
Name: kraken-class
Version: 0.0.3
Summary: Kraken class
Home-page: https://github.com/tactik8/kraken_class
Author: Tactik8
Author-email: info@tactik8.com
License: MIT
Platform: UNKNOWN
Classifier: License :: OSI Approved :: MIT License
Classifier: Programming Language :: Python :: 3
Classifier: Programming Language :: Python :: 3.8
Requires-Dist: kraken-record
Requires-Dist: kraken-db
Requires-Dist: kraken-cache
